PipeRider/VERSION
PipeRider/__init__.py
PipeRider/api/__init__.py
PipeRider/api/datasets.py
PipeRider/api/events.py
PipeRider/api/http_client.py
PipeRider/api/logger.py
PipeRider/api/models.py
PipeRider/api/projects.py
PipeRider/api/runs.py
PipeRider/api/users.py
PipeRider/testutils/__init__.py
piperider_python_sdk-0.0.5.dist-info/METADATA
piperider_python_sdk-0.0.5.dist-info/WHEEL
piperider_python_sdk-0.0.5.dist-info/top_level.txt
piperider_python_sdk-0.0.5.dist-info/RECORD
