Metadata-Version: 2.1
Name: piperider-python-sdk
Version: 0.0.5
Summary: PipeRider Python SDK
Home-page: https://github.com/InfuseAI/piperider-python-sdk
License: UNKNOWN
Project-URL: Bug Tracker, https://github.com/InfuseAI/piperider-python-sdk/issues
Platform: UNKNOWN
Classifier: Programming Language :: Python :: 3
Classifier: License :: OSI Approved :: Apache Software License
Classifier: Operating System :: OS Independent
Classifier: Development Status :: 4 - Beta
Requires-Python: >=3.6
Requires-Dist: requests
Requires-Dist: types-requests
Provides-Extra: dev
Requires-Dist: pytest (>=4.6) ; extra == 'dev'
Requires-Dist: pytest-flake8 ; extra == 'dev'
Requires-Dist: flake8 (==3.9.2) ; extra == 'dev'
Requires-Dist: pytest-cov ; extra == 'dev'
Requires-Dist: twine ; extra == 'dev'
Requires-Dist: boto3 ; extra == 'dev'
